eye_classifier/__init__.py
eye_classifier/eyeClassifierModel.py
eye_classifier/interface.py
eye_classifier/main.py
eye_classifier/test.py
eye_classifier/train.py
eye_detector/__init__.py
eye_detector/interface.py
eye_detector/main.py
face_detector/__init__.py
face_detector/analyze.py
face_detector/detect.py
face_detector/interface.py
face_detector/models.py
face_detector/test.py
face_detector/train.py
face_detector/utils/__init__.py
face_detector/utils/augmentations.py
face_detector/utils/datasets.py
face_detector/utils/logger.py
face_detector/utils/parse_config.py
face_detector/utils/utils.py
lrsphotos/__init__.py
lrsphotos/main.py
smile_classifier/__init__.py
smile_classifier/interface.py
smile_classifier/smile?.py
LRSPhotos-0.1.4.dist-info/METADATA
LRSPhotos-0.1.4.dist-info/WHEEL
LRSPhotos-0.1.4.dist-info/top_level.txt
LRSPhotos-0.1.4.dist-info/RECORD
